{"upload_date": "20210611", "extractor": "youtube", "height": 1440, "like_count": 263, "duration": 1338, "fulltitle": "688\uff1a\u6c11\u4e3b\u9017\u903c\u7684\u65b0\u5b66\u6f6e\u8fd0\u52a8\uff0c\u8138\u662f\u4e0d\u8981\u4e0d\u8981\u7684\u3002", "playlist_index": 168, "view_count": 4422, "playlist": "Spicy space - Videos", "average_rating": 4.8534799, "_filename": "20210611_uZwTJ3orJ4k.mp4", "tags": ["\u4e2d\u7f8e\u8d38\u6613\u6218", "\u9999\u6e2f\u53cd\u9001\u4e2d", "\u4e2d\u56fd\u7ecf\u6d4e", "\u5b54\u5b50", "\u8001\u5b50", "\u5112\u5bb6\u601d\u60f3", "\u4e2d\u56fd\u6587\u5316", "\u4e2d\u56fd\u4e13\u5236", "\u7231\u56fd\u7ea2\u86c6", "\u5229\u7528\u7f8e\u56fd\u6cd5\u5f8b", "\u5077\u6e21", "\u5ddd\u666e", "\u7f8e\u56fd\u5927\u9009", "\u7279\u6717\u666e", "\u4eba\u6c11\u5e01\u8d2c\u503c", "\u65b0\u79fb\u6c11\u751f\u6d3b", "\u7f8e\u56fd\u79fb\u6c11\u751f", "\u4eba\u6c11\u5e01\u5d29\u76d8", "\u7f8e\u5143\u5347\u503c", "\u6c11\u4e3b\u4e0e\u81ea\u6cbb", "\u4e2d\u56fd\u4e92\u8054\u7f51", "\u9999\u6e2f\u8b66\u5bdf", "\u7ea2\u7c89", "\u6587\u9769\u7c89", "\u6c11\u65cf\u4e3b\u4e49\u7c89", "\u5171\u4ea7\u515a", "\u56fd\u6c11\u515a", "\u53f0\u6e7e\u6c11\u4e3b\u8fd0\u52a8", "\u4e2d\u56fd\u6c11\u4e3b\u8fd0\u52a8", "\u7f8e\u56fd\u5171\u548c\u515a", "\u7f8e\u56fd\u6c11\u4e3b\u515a", "2020\u5341\u5927\u9884\u8a00", "WTO", "\u4ea1\u56fd\u5974", "\u534e\u4e3a", "\u7f8e\u56fd\u5236\u88c1", "\u7f8e\u56fd\u5386\u53f2", "\u4e2d\u56fd\u5386\u53f2", "\u82f1\u56fd\u8131\u6b27", "\u7f8e\u56fd\u56fd\u4f1a", "\u7f8e\u56fd\u6cd5\u6848", "\u4eba\u6743\u7ec4\u7ec7", "\u601d\u60f3\u4e0e\u89e3\u653e", "\u72ec\u7acb\u601d\u8003", "\u6556\u6b4c", "\u4f5c\u5bb6\u91d1\u521a\u77f3", "\u8521\u82f1\u6587", "\u9a6c\u82f1\u4e5d", "\u4e60\u8fd1\u5e73", "\u4e2d\u56fd\u72d7\u7cae", "\u673a\u5668\u7c89", "\u5e74\u4ee3\u5411\u94b1\u770b", "\u4e94\u5cb3\u6563\u4eba", "\u8d3a\u536b\u65b9", "\u65af\u97e6\u6c5f", "\u6d66\u5fd7\u5f3a", "\u6c6a\u7cbe\u536b", "\u56db\u5ddd\u666e\u901a\u8bdd", "\u6bdb\u6cfd\u4e1c", "\u65b0\u79fb\u6c11", "\u7f8e\u56fd\u79fb\u6c11", "\u4e2d\u56fd\u4eba\u6743", "\u65e5\u672c\u516c\u4e3b\u53f7\u90ae\u8f6e", "\u7f8e\u56fd\u5236\u88c1\u4e2d\u56fd", "\u4eba\u8138\u8bc6\u522b", "\u4e2d\u7f8e\u8131\u52fe", "\u4e2d\u56fd\u732a\u8089\u6da8\u4ef7", "\u6b66\u6c49", "\u6cd5\u6cbb\u4e0e\u4eba\u5236", "\u9999\u6e2f\u8f6e\u9677", "\u56fd\u5bb6\u5b89\u5168", "\u77e5\u8bc6\u4ea7\u6743", "\u534e\u4e3a\u76d7\u7a83", "\u7535\u89c6\u8ba4\u7f6a", "\u8001\u5d14\u8336\u9986", "\u79c0\u67285", "\u4e2d\u56fd\u7ea2\u86c6", "\u4e0a\u6d77\u5c01\u57ce", "\u4e2d\u56fd\u56fd\u6c11\u515a", "\u53f0\u6e7e\u6c11\u8fdb\u515a", "CCP", "\u534e\u4eba\u5728\u7f8e\u56fd", "\u73b0\u8c61\u5b66", "\u83cc\u6b66"], "is_live": null, "id": "uZwTJ3orJ4k", "dislike_count": 10, "playlist_id": "UC7AyG3ABC8DPTDSe7jWSzHA", "abr": 129.475, "uploader_url": "http://www.youtube.com/channel/UC7AyG3ABC8DPTDSe7jWSzHA", "fps": 25, "stretched_ratio": null, "channel_url": "https://www.youtube.com/channel/UC7AyG3ABC8DPTDSe7jWSzHA", "thumbnail": "https://i.ytimg.com/vi/uZwTJ3orJ4k/hqdefault.jpg?sqp=-oaymwEcCNACELwBSFXyq4qpAw4IARUAAIhCGAFwAcABBg==&rs=AOn4CLCPXeNoGJkOFi9YPWwGGN3GRK6Klw", "webpage_url_basename": "uZwTJ3orJ4k", "acodec": "mp4a.40.2", "display_id": "uZwTJ3orJ4k", "description": "#\u6c11\u4e3b\u9017\u903c#\u65b0\u5b66\u6f6e#\u4e8c\u7ea7\u5b66\u9662\n\u5492\u8bed\uff1a\u53d1\u51fa\u6765\u4e0d\u770b\u5c31\u70b9\u8e29\u7684\u4eba\u5176\u59bb\u5973\u88ab\u8f6e\u5978\u540e\u5168\u5bb6\u6b7b\u7edd\u3002\u6211\u4fe1\u795e\u7684\uff0c\u5492\u8bed\u8d85\u7075\u5e94\uff01\n\u81ea\u6211\u4ecb\u7ecd\n\u59d3\u540d\uff1a\u770b\u5de6\u4e0a\u65b9\n\u6027\u522b\uff1a\u5f53\u7136\u4e0d\u662f\u5973\u7684\n\u751f\u65e5\uff1a365\u5929\u91cc\u7684\u9f99\u65e5\u5929\n\u5c5e\u76f8\uff1a\u975e\u5e38\u8363\u5e78\u5c5e\u51e4\u51f0\n\u5b66\u5386\u3000\uff1a\u53cd\u6b63\u4e0d\u662f\u535a\u58eb\n\u804c\u4e1a\u3000\uff1a\u5143\u5e1d\u56fd\u4e0d\u5982\u5993\u5973\n\u559c\u6b22\u6ef4\u540d\u4eba\uff1a\u8001\u5b50\uff01\n\u6700\u559c\u6b22\u6ef4\u5b57\uff1a\u62c6\n\u6700\u559c\u6b22\u6ef4\u4e8b\uff1a\u6545\u5c45\u4e0a\uff0c\u81ea\u711a\uff01\n\u4e09\u89c2\u52a0\u4e00\u89c2\n\u4eba\u751f\u89c2\uff1a\u4e00\u76f4\u4ee5\u4e3a\uff0c\u5439\u725b\u662f\u4e00\u95e8\u5f88\u6709\u524d\u9014\u7684\u804c\u4e1a\uff01\n\u4ef7\u503c\u89c2\uff1a\u559c\u6b22\u770b\u8111\u5b50\u88ab\u95e8\u5939\u7740\u7684\u4eba\uff0c\u559c\u6b22\u770b\u5634\u5df4\u6bd4\u8138\u5927\u7684\u4eba\uff01\n\u4e16\u754c\u89c2\uff1a\u8001\u5b50\u662f\u601d\u60f3\u5bb6\uff0c\u4e0d\u4fe1\u4f60\u95ee\u8001\u5b50\uff01\n\u60b2\u559c\u89c2\uff1a\u4eba\u8fd9\u4e00\u751f\u80fd\u641e\u51fa\u4e9b\u4ec0\u4e48?\u4e0d\u5916\u4e4e\u6709\u4e8c\uff1a\u7537\u4eba\u625b\u7740\u5973\u4eba\u3001\u94b1\u548c\u540d\u88ab\u4e00\u6839\u7a3b\u8349\u538b\u6b7b\uff0c\u800c\u5973\u4eba\uff0c\u5f80\u98ce\u666f\u5904\u4e00\u7ad9\uff0c\u5373\u53ef\u7b11\u50b2\u6c5f\u6e56\uff01\n\u8054\u7cfb\u65b9\u5f0f\n\u6211\u7684\u90ae\u7bb1\u662fwto5185188@gmail\uff08\u5efa\u8bae\u5899\u5185\u670b\u53cb\u4e0d\u8981\u8bc4\u8bba\u8fc7\u706b\u7684\u8bdd\uff0c\u7ed9\u6211\u5199\u90ae\u4ef6\u624d\u5b89\u5168\uff09\n\u6211\u7684\u817f\u817f\u513f\u8d26\u53f7\u662f\uff1awto518\n\u8138\u4e66ID\u53eb\uff1aDiamond John", "format": "400 - 2560x1440 (1440p)+140 - audio only (tiny)", "playlist_uploader": null, "uploader": "\u9ebb\u8fa3\u7a7a\u95f4", "format_id": "400+140", "uploader_id": "UC7AyG3ABC8DPTDSe7jWSzHA", "categories": ["News & Politics"], "playlist_title": "Spicy space - Videos", "thumbnails": [{"url": "https://i.ytimg.com/vi/uZwTJ3orJ4k/hqdefault.jpg?sqp=-oaymwEbCKgBEF5IVfKriqkDDggBFQAAiEIYAXABwAEG&rs=AOn4CLBMaI27kNvJCnI-usx04GUSN3JFhQ", "width": 168, "resolution": "168x94", "id": "0", "height": 94}, {"url": "https://i.ytimg.com/vi/uZwTJ3orJ4k/hqdefault.jpg?sqp=-oaymwEbCMQBEG5IVfKriqkDDggBFQAAiEIYAXABwAEG&rs=AOn4CLDVjMI31pkAtLz4LojIa8HMWc2ORg", "width": 196, "resolution": "196x110", "id": "1", "height": 110}, {"url": "https://i.ytimg.com/vi/uZwTJ3orJ4k/hqdefault.jpg?sqp=-oaymwEcCPYBEIoBSFXyq4qpAw4IARUAAIhCGAFwAcABBg==&rs=AOn4CLBk8UOupWFfwIFsomVhdovWUuvXlg", "width": 246, "resolution": "246x138", "id": "2", "height": 138}, {"url": "https://i.ytimg.com/vi/uZwTJ3orJ4k/hqdefault.jpg?sqp=-oaymwEcCNACELwBSFXyq4qpAw4IARUAAIhCGAFwAcABBg==&rs=AOn4CLCPXeNoGJkOFi9YPWwGGN3GRK6Klw", "width": 336, "resolution": "336x188", "id": "3", "height": 188}], "channel_id": "UC7AyG3ABC8DPTDSe7jWSzHA", "extractor_key": "Youtube", "vcodec": "av01.0.12M.08", "title": "688\uff1a\u6c11\u4e3b\u9017\u903c\u7684\u65b0\u5b66\u6f6e\u8fd0\u52a8\uff0c\u8138\u662f\u4e0d\u8981\u4e0d\u8981\u7684\u3002", "vbr": 3254.54, "ext": "mp4", "channel": "Spicy space", "webpage_url": "https://www.youtube.com/watch?v=uZwTJ3orJ4k", "formats": [{"asr": 48000, "format_note": "tiny", "protocol": "https", "format": "249 - audio only (tiny)", "tbr": 49.728, "height": null, "downloader_options": {"http_chunk_size": 10485760}, "format_id": "249", "quality": 0, "container": "webm_dash", "http_headers": {"Accept-Charset": "ISO-8859-1,utf-8;q=0.7,*;q=0.7", "Accept-Language": "en-us,en;q=0.5", "Accept-Encoding": "gzip, deflate", "Accept": "text/html,application/xhtml+xml,application/xml;q=0.9,*/*;q=0.8", "User-Agent": "Mozilla/5.0 (Windows NT 10.0; Win64; x64) AppleWebKit/537.36 (KHTML, like Gecko) Chrome/71.0.3578.126 Safari/537.36"}, "url": "https://r2---sn-vgqsknlk.googlevideo.com/videoplayback?expire=1633505259&ei=i_tcYf7RIIiHuQKptJCACw&ip=69.136.135.75&id=o-AJdmr52t8tPQSO674EhiY4P6Z1NXRWqk0fxNUGYJ7Uf3&itag=249&source=youtube&requiressl=yes&mh=gH&mm=31%2C26&mn=sn-vgqsknlk%2Csn-p5qs7n7z&ms=au%2Conr&mv=m&mvi=2&pl=19&initcwndbps=1862500&vprv=1&mime=audio%2Fwebm&ns=hpEngF8VdK4un1lwqFxr5v4G&gir=yes&clen=8319741&dur=1338.421&lmt=1623471360797662&mt=1633483256&fvip=2&keepalive=yes&fexp=24001373%2C24007246&c=WEB&txp=5411222&n=b05Z2SjnPsafJdGn&sparams=expire%2Cei%2Cip%2Cid%2Citag%2Csource%2Crequiressl%2Cvprv%2Cmime%2Cns%2Cgir%2Cclen%2Cdur%2Clmt&sig=AOq0QJ8wRQIgQ8dw3om5nyqOrjS2dkFv_JszID6wFhoH9t2YyDjswmoCIQDc5mf3PQzp75XFiMxWpttA3X_kEd4zYLm4vMX3nWskhw%3D%3D&lsparams=mh%2Cmm%2Cmn%2Cms%2Cmv%2Cmvi%2Cpl%2Cinitcwndbps&lsig=AG3C_xAwRgIhAIvXvSdhgfnGzXdm5n14CV0O5sPvOlvd3S8O_LYNbllYAiEAkiOwAFx9n9UN7HaBH74Bk59OOUOqK8o1OOOpmw0fkNI%3D", "vcodec": "none", "abr": 49.728, "width": null, "ext": "webm", "filesize": 8319741, "fps": null, "acodec": "opus"}, {"asr": 48000, "format_note": "tiny", "protocol": "https", "format": "250 - audio only (tiny)", "tbr": 60.48, "height": null, "downloader_options": {"http_chunk_size": 10485760}, "format_id": "250", "quality": 0, "container": "webm_dash", "http_headers": {"Accept-Charset": "ISO-8859-1,utf-8;q=0.7,*;q=0.7", "Accept-Language": "en-us,en;q=0.5", "Accept-Encoding": "gzip, deflate", "Accept": "text/html,application/xhtml+xml,application/xml;q=0.9,*/*;q=0.8", "User-Agent": "Mozilla/5.0 (Windows NT 10.0; Win64; x64) AppleWebKit/537.36 (KHTML, like Gecko) Chrome/71.0.3578.126 Safari/537.36"}, "url": "https://r2---sn-vgqsknlk.googlevideo.com/videoplayback?expire=1633505259&ei=i_tcYf7RIIiHuQKptJCACw&ip=69.136.135.75&id=o-AJdmr52t8tPQSO674EhiY4P6Z1NXRWqk0fxNUGYJ7Uf3&itag=250&source=youtube&requiressl=yes&mh=gH&mm=31%2C26&mn=sn-vgqsknlk%2Csn-p5qs7n7z&ms=au%2Conr&mv=m&mvi=2&pl=19&initcwndbps=1862500&vprv=1&mime=audio%2Fwebm&ns=hpEngF8VdK4un1lwqFxr5v4G&gir=yes&clen=10118600&dur=1338.421&lmt=1623471335063829&mt=1633483256&fvip=2&keepalive=yes&fexp=24001373%2C24007246&c=WEB&txp=5411222&n=b05Z2SjnPsafJdGn&sparams=expire%2Cei%2Cip%2Cid%2Citag%2Csource%2Crequiressl%2Cvprv%2Cmime%2Cns%2Cgir%2Cclen%2Cdur%2Clmt&sig=AOq0QJ8wRgIhAJzH30FE75NeJ-ubb9YNUjtHkrlmcSbFA7O6FvxG6oqwAiEAkHDj4T5F6mZU8oH0KDe6LoKCpp-E9z5WmaMOlmxdbnE%3D&lsparams=mh%2Cmm%2Cmn%2Cms%2Cmv%2Cmvi%2Cpl%2Cinitcwndbps&lsig=AG3C_xAwRgIhAIvXvSdhgfnGzXdm5n14CV0O5sPvOlvd3S8O_LYNbllYAiEAkiOwAFx9n9UN7HaBH74Bk59OOUOqK8o1OOOpmw0fkNI%3D", "vcodec": "none", "abr": 60.48, "width": null, "ext": "webm", "filesize": 10118600, "fps": null, "acodec": "opus"}, {"asr": 48000, "format_note": "tiny", "protocol": "https", "format": "251 - audio only (tiny)", "tbr": 110.187, "height": null, "downloader_options": {"http_chunk_size": 10485760}, "format_id": "251", "quality": 0, "container": "webm_dash", "http_headers": {"Accept-Charset": "ISO-8859-1,utf-8;q=0.7,*;q=0.7", "Accept-Language": "en-us,en;q=0.5", "Accept-Encoding": "gzip, deflate", "Accept": "text/html,application/xhtml+xml,application/xml;q=0.9,*/*;q=0.8", "User-Agent": "Mozilla/5.0 (Windows NT 10.0; Win64; x64) AppleWebKit/537.36 (KHTML, like Gecko) Chrome/71.0.3578.126 Safari/537.36"}, "url": "https://r2---sn-vgqsknlk.googlevideo.com/videoplayback?expire=1633505259&ei=i_tcYf7RIIiHuQKptJCACw&ip=69.136.135.75&id=o-AJdmr52t8tPQSO674EhiY4P6Z1NXRWqk0fxNUGYJ7Uf3&itag=251&source=youtube&requiressl=yes&mh=gH&mm=31%2C26&mn=sn-vgqsknlk%2Csn-p5qs7n7z&ms=au%2Conr&mv=m&mvi=2&pl=19&initcwndbps=1862500&vprv=1&mime=audio%2Fwebm&ns=hpEngF8VdK4un1lwqFxr5v4G&gir=yes&clen=18434704&dur=1338.421&lmt=1623471345003161&mt=1633483256&fvip=2&keepalive=yes&fexp=24001373%2C24007246&c=WEB&txp=5411222&n=b05Z2SjnPsafJdGn&sparams=expire%2Cei%2Cip%2Cid%2Citag%2Csource%2Crequiressl%2Cvprv%2Cmime%2Cns%2Cgir%2Cclen%2Cdur%2Clmt&sig=AOq0QJ8wRQIhAMKw8StFxD08UlWZ4FlAJJwhQQr5SYBx1xMwJ07YsV2AAiANvwizWoJvbB1nbnK4kObXQJs5FUgAoszvOelWUtltsg%3D%3D&lsparams=mh%2Cmm%2Cmn%2Cms%2Cmv%2Cmvi%2Cpl%2Cinitcwndbps&lsig=AG3C_xAwRgIhAIvXvSdhgfnGzXdm5n14CV0O5sPvOlvd3S8O_LYNbllYAiEAkiOwAFx9n9UN7HaBH74Bk59OOUOqK8o1OOOpmw0fkNI%3D", "vcodec": "none", "abr": 110.187, "width": null, "ext": "webm", "filesize": 18434704, "fps": null, "acodec": "opus"}, {"asr": 44100, "format_note": "tiny", "protocol": "https", "format": "140 - audio only (tiny)", "tbr": 129.475, "height": null, "downloader_options": {"http_chunk_size": 10485760}, "format_id": "140", "quality": 0, "container": "m4a_dash", "http_headers": {"Accept-Charset": "ISO-8859-1,utf-8;q=0.7,*;q=0.7", "Accept-Language": "en-us,en;q=0.5", "Accept-Encoding": "gzip, deflate", "Accept": "text/html,application/xhtml+xml,application/xml;q=0.9,*/*;q=0.8", "User-Agent": "Mozilla/5.0 (Windows NT 10.0; Win64; x64) AppleWebKit/537.36 (KHTML, like Gecko) Chrome/71.0.3578.126 Safari/537.36"}, "url": "https://r2---sn-vgqsknlk.googlevideo.com/videoplayback?expire=1633505259&ei=i_tcYf7RIIiHuQKptJCACw&ip=69.136.135.75&id=o-AJdmr52t8tPQSO674EhiY4P6Z1NXRWqk0fxNUGYJ7Uf3&itag=140&source=youtube&requiressl=yes&mh=gH&mm=31%2C26&mn=sn-vgqsknlk%2Csn-p5qs7n7z&ms=au%2Conr&mv=m&mvi=2&pl=19&initcwndbps=1862500&vprv=1&mime=audio%2Fmp4&ns=hpEngF8VdK4un1lwqFxr5v4G&gir=yes&clen=21662381&dur=1338.467&lmt=1623497406024769&mt=1633483256&fvip=2&keepalive=yes&fexp=24001373%2C24007246&c=WEB&txp=5432434&n=b05Z2SjnPsafJdGn&sparams=expire%2Cei%2Cip%2Cid%2Citag%2Csource%2Crequiressl%2Cvprv%2Cmime%2Cns%2Cgir%2Cclen%2Cdur%2Clmt&sig=AOq0QJ8wRAIgPrZzQ_W7zZWivBZYtIrZnL_f1EUBdpjufN66cGkCKLECIFrXrw5J63V1RvCDT16AuVtuqqITBDIuPLrbTbZai2GF&lsparams=mh%2Cmm%2Cmn%2Cms%2Cmv%2Cmvi%2Cpl%2Cinitcwndbps&lsig=AG3C_xAwRgIhAIvXvSdhgfnGzXdm5n14CV0O5sPvOlvd3S8O_LYNbllYAiEAkiOwAFx9n9UN7HaBH74Bk59OOUOqK8o1OOOpmw0fkNI%3D", "vcodec": "none", "abr": 129.475, "width": null, "ext": "m4a", "filesize": 21662381, "fps": null, "acodec": "mp4a.40.2"}, {"asr": null, "format_note": "144p", "protocol": "https", "format": "160 - 256x144 (144p)", "tbr": 37.231, "height": 144, "downloader_options": {"http_chunk_size": 10485760}, "format_id": "160", "quality": 0, "container": "mp4_dash", "vbr": 37.231, "url": "https://r2---sn-vgqsknlk.googlevideo.com/videoplayback?expire=1633505259&ei=i_tcYf7RIIiHuQKptJCACw&ip=69.136.135.75&id=o-AJdmr52t8tPQSO674EhiY4P6Z1NXRWqk0fxNUGYJ7Uf3&itag=160&aitags=133%2C134%2C135%2C136%2C137%2C160%2C242%2C243%2C244%2C247%2C248%2C271%2C278%2C394%2C395%2C396%2C397%2C398%2C399%2C400&source=youtube&requiressl=yes&mh=gH&mm=31%2C26&mn=sn-vgqsknlk%2Csn-p5qs7n7z&ms=au%2Conr&mv=m&mvi=2&pl=19&initcwndbps=1862500&vprv=1&mime=video%2Fmp4&ns=hpEngF8VdK4un1lwqFxr5v4G&gir=yes&clen=6228633&dur=1338.360&lmt=1623499015616098&mt=1633483256&fvip=2&keepalive=yes&fexp=24001373%2C24007246&c=WEB&txp=5432434&n=b05Z2SjnPsafJdGn&sparams=expire%2Cei%2Cip%2Cid%2Caitags%2Csource%2Crequiressl%2Cvprv%2Cmime%2Cns%2Cgir%2Cclen%2Cdur%2Clmt&sig=AOq0QJ8wRgIhAMwl8nksqSeQ2KfoMigWOSlMdpz6XFzXsAFaBYaVqn6NAiEA5nGYkvshQpSHYNMEOOq8S-OrvkJkXjjNGvJHxOSSugc%3D&lsparams=mh%2Cmm%2Cmn%2Cms%2Cmv%2Cmvi%2Cpl%2Cinitcwndbps&lsig=AG3C_xAwRgIhAIvXvSdhgfnGzXdm5n14CV0O5sPvOlvd3S8O_LYNbllYAiEAkiOwAFx9n9UN7HaBH74Bk59OOUOqK8o1OOOpmw0fkNI%3D", "vcodec": "avc1.4d400c", "http_headers": {"Accept-Charset": "ISO-8859-1,utf-8;q=0.7,*;q=0.7", "Accept-Language": "en-us,en;q=0.5", "Accept-Encoding": "gzip, deflate", "Accept": "text/html,application/xhtml+xml,application/xml;q=0.9,*/*;q=0.8", "User-Agent": "Mozilla/5.0 (Windows NT 10.0; Win64; x64) AppleWebKit/537.36 (KHTML, like Gecko) Chrome/71.0.3578.126 Safari/537.36"}, "width": 256, "ext": "mp4", "filesize": 6228633, "fps": 25, "acodec": "none"}, {"asr": null, "format_note": "144p", "protocol": "https", "format": "278 - 256x144 (144p)", "tbr": 77.322, "height": 144, "downloader_options": {"http_chunk_size": 10485760}, "format_id": "278", "quality": 0, "container": "webm_dash", "vbr": 77.322, "url": "https://r2---sn-vgqsknlk.googlevideo.com/videoplayback?expire=1633505259&ei=i_tcYf7RIIiHuQKptJCACw&ip=69.136.135.75&id=o-AJdmr52t8tPQSO674EhiY4P6Z1NXRWqk0fxNUGYJ7Uf3&itag=278&aitags=133%2C134%2C135%2C136%2C137%2C160%2C242%2C243%2C244%2C247%2C248%2C271%2C278%2C394%2C395%2C396%2C397%2C398%2C399%2C400&source=youtube&requiressl=yes&mh=gH&mm=31%2C26&mn=sn-vgqsknlk%2Csn-p5qs7n7z&ms=au%2Conr&mv=m&mvi=2&pl=19&initcwndbps=1862500&vprv=1&mime=video%2Fwebm&ns=hpEngF8VdK4un1lwqFxr5v4G&gir=yes&clen=12935746&dur=1338.360&lmt=1623500694476698&mt=1633483256&fvip=2&keepalive=yes&fexp=24001373%2C24007246&c=WEB&txp=5432434&n=b05Z2SjnPsafJdGn&sparams=expire%2Cei%2Cip%2Cid%2Caitags%2Csource%2Crequiressl%2Cvprv%2Cmime%2Cns%2Cgir%2Cclen%2Cdur%2Clmt&sig=AOq0QJ8wRQIgFEvwjEa46Pm5kRo1EPEkCqAV-0iqKdquz2uyj3OWD74CIQC1dWunP7xTO4Y-u3e2_vUCUGwi1UVIVmGKcFFysR_ciA%3D%3D&lsparams=mh%2Cmm%2Cmn%2Cms%2Cmv%2Cmvi%2Cpl%2Cinitcwndbps&lsig=AG3C_xAwRgIhAIvXvSdhgfnGzXdm5n14CV0O5sPvOlvd3S8O_LYNbllYAiEAkiOwAFx9n9UN7HaBH74Bk59OOUOqK8o1OOOpmw0fkNI%3D", "vcodec": "vp9", "http_headers": {"Accept-Charset": "ISO-8859-1,utf-8;q=0.7,*;q=0.7", "Accept-Language": "en-us,en;q=0.5", "Accept-Encoding": "gzip, deflate", "Accept": "text/html,application/xhtml+xml,application/xml;q=0.9,*/*;q=0.8", "User-Agent": "Mozilla/5.0 (Windows NT 10.0; Win64; x64) AppleWebKit/537.36 (KHTML, like Gecko) Chrome/71.0.3578.126 Safari/537.36"}, "width": 256, "ext": "webm", "filesize": 12935746, "fps": 25, "acodec": "none"}, {"asr": null, "format_note": "144p", "protocol": "https", "format": "394 - 256x144 (144p)", "tbr": 86.265, "height": 144, "downloader_options": {"http_chunk_size": 10485760}, "format_id": "394", "quality": 0, "container": "mp4_dash", "vbr": 86.265, "url": "https://r2---sn-vgqsknlk.googlevideo.com/videoplayback?expire=1633505259&ei=i_tcYf7RIIiHuQKptJCACw&ip=69.136.135.75&id=o-AJdmr52t8tPQSO674EhiY4P6Z1NXRWqk0fxNUGYJ7Uf3&itag=394&aitags=133%2C134%2C135%2C136%2C137%2C160%2C242%2C243%2C244%2C247%2C248%2C271%2C278%2C394%2C395%2C396%2C397%2C398%2C399%2C400&source=youtube&requiressl=yes&mh=gH&mm=31%2C26&mn=sn-vgqsknlk%2Csn-p5qs7n7z&ms=au%2Conr&mv=m&mvi=2&pl=19&initcwndbps=1862500&vprv=1&mime=video%2Fmp4&ns=hpEngF8VdK4un1lwqFxr5v4G&gir=yes&clen=14431812&dur=1338.360&lmt=1623581107775624&mt=1633483256&fvip=2&keepalive=yes&fexp=24001373%2C24007246&c=WEB&txp=5436432&n=b05Z2SjnPsafJdGn&sparams=expire%2Cei%2Cip%2Cid%2Caitags%2Csource%2Crequiressl%2Cvprv%2Cmime%2Cns%2Cgir%2Cclen%2Cdur%2Clmt&sig=AOq0QJ8wRgIhALcvkbihnJtWuN06Ep6-V0z_BGg-doW7xCleMQ4BAOYNAiEAz7c_0YzYq-rQ16PgDRckpPTgvUJnRSB7rzZ7w-4rPMQ%3D&lsparams=mh%2Cmm%2Cmn%2Cms%2Cmv%2Cmvi%2Cpl%2Cinitcwndbps&lsig=AG3C_xAwRgIhAIvXvSdhgfnGzXdm5n14CV0O5sPvOlvd3S8O_LYNbllYAiEAkiOwAFx9n9UN7HaBH74Bk59OOUOqK8o1OOOpmw0fkNI%3D", "vcodec": "av01.0.00M.08", "http_headers": {"Accept-Charset": "ISO-8859-1,utf-8;q=0.7,*;q=0.7", "Accept-Language": "en-us,en;q=0.5", "Accept-Encoding": "gzip, deflate", "Accept": "text/html,application/xhtml+xml,application/xml;q=0.9,*/*;q=0.8", "User-Agent": "Mozilla/5.0 (Windows NT 10.0; Win64; x64) AppleWebKit/537.36 (KHTML, like Gecko) Chrome/71.0.3578.126 Safari/537.36"}, "width": 256, "ext": "mp4", "filesize": 14431812, "fps": 25, "acodec": "none"}, {"asr": null, "format_note": "240p", "protocol": "https", "format": "133 - 426x240 (240p)", "tbr": 69.996, "height": 240, "downloader_options": {"http_chunk_size": 10485760}, "format_id": "133", "quality": 1, "container": "mp4_dash", "vbr": 69.996, "url": "https://r2---sn-vgqsknlk.googlevideo.com/videoplayback?expire=1633505259&ei=i_tcYf7RIIiHuQKptJCACw&ip=69.136.135.75&id=o-AJdmr52t8tPQSO674EhiY4P6Z1NXRWqk0fxNUGYJ7Uf3&itag=133&aitags=133%2C134%2C135%2C136%2C137%2C160%2C242%2C243%2C244%2C247%2C248%2C271%2C278%2C394%2C395%2C396%2C397%2C398%2C399%2C400&source=youtube&requiressl=yes&mh=gH&mm=31%2C26&mn=sn-vgqsknlk%2Csn-p5qs7n7z&ms=au%2Conr&mv=m&mvi=2&pl=19&initcwndbps=1862500&vprv=1&mime=video%2Fmp4&ns=hpEngF8VdK4un1lwqFxr5v4G&gir=yes&clen=11710056&dur=1338.360&lmt=1623498546506591&mt=1633483256&fvip=2&keepalive=yes&fexp=24001373%2C24007246&c=WEB&txp=5432434&n=b05Z2SjnPsafJdGn&sparams=expire%2Cei%2Cip%2Cid%2Caitags%2Csource%2Crequiressl%2Cvprv%2Cmime%2Cns%2Cgir%2Cclen%2Cdur%2Clmt&sig=AOq0QJ8wRAIgDnoHNRvhgON0U8LRu1mssJOd2TdthFdckCjG1lTg0OQCIASMeHKAOaUmS7L34XPFIgStg5FTmcRe6qVZ_900kYCu&lsparams=mh%2Cmm%2Cmn%2Cms%2Cmv%2Cmvi%2Cpl%2Cinitcwndbps&lsig=AG3C_xAwRgIhAIvXvSdhgfnGzXdm5n14CV0O5sPvOlvd3S8O_LYNbllYAiEAkiOwAFx9n9UN7HaBH74Bk59OOUOqK8o1OOOpmw0fkNI%3D", "vcodec": "avc1.4d4015", "http_headers": {"Accept-Charset": "ISO-8859-1,utf-8;q=0.7,*;q=0.7", "Accept-Language": "en-us,en;q=0.5", "Accept-Encoding": "gzip, deflate", "Accept": "text/html,application/xhtml+xml,application/xml;q=0.9,*/*;q=0.8", "User-Agent": "Mozilla/5.0 (Windows NT 10.0; Win64; x64) AppleWebKit/537.36 (KHTML, like Gecko) Chrome/71.0.3578.126 Safari/537.36"}, "width": 426, "ext": "mp4", "filesize": 11710056, "fps": 25, "acodec": "none"}, {"asr": null, "format_note": "240p", "protocol": "https", "format": "242 - 426x240 (240p)", "tbr": 102.088, "height": 240, "downloader_options": {"http_chunk_size": 10485760}, "format_id": "242", "quality": 1, "container": "webm_dash", "vbr": 102.088, "url": "https://r2---sn-vgqsknlk.googlevideo.com/videoplayback?expire=1633505259&ei=i_tcYf7RIIiHuQKptJCACw&ip=69.136.135.75&id=o-AJdmr52t8tPQSO674EhiY4P6Z1NXRWqk0fxNUGYJ7Uf3&itag=242&aitags=133%2C134%2C135%2C136%2C137%2C160%2C242%2C243%2C244%2C247%2C248%2C271%2C278%2C394%2C395%2C396%2C397%2C398%2C399%2C400&source=youtube&requiressl=yes&mh=gH&mm=31%2C26&mn=sn-vgqsknlk%2Csn-p5qs7n7z&ms=au%2Conr&mv=m&mvi=2&pl=19&initcwndbps=1862500&vprv=1&mime=video%2Fwebm&ns=hpEngF8VdK4un1lwqFxr5v4G&gir=yes&clen=17078953&dur=1338.360&lmt=1623500632935282&mt=1633483256&fvip=2&keepalive=yes&fexp=24001373%2C24007246&c=WEB&txp=5432434&n=b05Z2SjnPsafJdGn&sparams=expire%2Cei%2Cip%2Cid%2Caitags%2Csource%2Crequiressl%2Cvprv%2Cmime%2Cns%2Cgir%2Cclen%2Cdur%2Clmt&sig=AOq0QJ8wRgIhAPJ3mPZNCGV1XjGJA6Hc4ZCdTvGXnLMXhGHN7ZFEu0IwAiEAlD5vYoJHdCcF6xOEdpewZN-JyeXA7wXPFYOyWmI79vM%3D&lsparams=mh%2Cmm%2Cmn%2Cms%2Cmv%2Cmvi%2Cpl%2Cinitcwndbps&lsig=AG3C_xAwRgIhAIvXvSdhgfnGzXdm5n14CV0O5sPvOlvd3S8O_LYNbllYAiEAkiOwAFx9n9UN7HaBH74Bk59OOUOqK8o1OOOpmw0fkNI%3D", "vcodec": "vp9", "http_headers": {"Accept-Charset": "ISO-8859-1,utf-8;q=0.7,*;q=0.7", "Accept-Language": "en-us,en;q=0.5", "Accept-Encoding": "gzip, deflate", "Accept": "text/html,application/xhtml+xml,application/xml;q=0.9,*/*;q=0.8", "User-Agent": "Mozilla/5.0 (Windows NT 10.0; Win64; x64) AppleWebKit/537.36 (KHTML, like Gecko) Chrome/71.0.3578.126 Safari/537.36"}, "width": 426, "ext": "webm", "filesize": 17078953, "fps": 25, "acodec": "none"}, {"asr": null, "format_note": "240p", "protocol": "https", "format": "395 - 426x240 (240p)", "tbr": 176.564, "height": 240, "downloader_options": {"http_chunk_size": 10485760}, "format_id": "395", "quality": 1, "container": "mp4_dash", "vbr": 176.564, "url": "https://r2---sn-vgqsknlk.googlevideo.com/videoplayback?expire=1633505259&ei=i_tcYf7RIIiHuQKptJCACw&ip=69.136.135.75&id=o-AJdmr52t8tPQSO674EhiY4P6Z1NXRWqk0fxNUGYJ7Uf3&itag=395&aitags=133%2C134%2C135%2C136%2C137%2C160%2C242%2C243%2C244%2C247%2C248%2C271%2C278%2C394%2C395%2C396%2C397%2C398%2C399%2C400&source=youtube&requiressl=yes&mh=gH&mm=31%2C26&mn=sn-vgqsknlk%2Csn-p5qs7n7z&ms=au%2Conr&mv=m&mvi=2&pl=19&initcwndbps=1862500&vprv=1&mime=video%2Fmp4&ns=hpEngF8VdK4un1lwqFxr5v4G&gir=yes&clen=29538411&dur=1338.360&lmt=1623581103957386&mt=1633483256&fvip=2&keepalive=yes&fexp=24001373%2C24007246&c=WEB&txp=5436432&n=b05Z2SjnPsafJdGn&sparams=expire%2Cei%2Cip%2Cid%2Caitags%2Csource%2Crequiressl%2Cvprv%2Cmime%2Cns%2Cgir%2Cclen%2Cdur%2Clmt&sig=AOq0QJ8wRQIhAN4JyjVmKLxq32dh3JXnAI00SoguqAu0OklzdJtEud_tAiB4pXNVnC3N1q085RFj5YtGoYuEu4CM2OIwSJj7jW-zpQ%3D%3D&lsparams=mh%2Cmm%2Cmn%2Cms%2Cmv%2Cmvi%2Cpl%2Cinitcwndbps&lsig=AG3C_xAwRgIhAIvXvSdhgfnGzXdm5n14CV0O5sPvOlvd3S8O_LYNbllYAiEAkiOwAFx9n9UN7HaBH74Bk59OOUOqK8o1OOOpmw0fkNI%3D", "vcodec": "av01.0.00M.08", "http_headers": {"Accept-Charset": "ISO-8859-1,utf-8;q=0.7,*;q=0.7", "Accept-Language": "en-us,en;q=0.5", "Accept-Encoding": "gzip, deflate", "Accept": "text/html,application/xhtml+xml,application/xml;q=0.9,*/*;q=0.8", "User-Agent": "Mozilla/5.0 (Windows NT 10.0; Win64; x64) AppleWebKit/537.36 (KHTML, like Gecko) Chrome/71.0.3578.126 Safari/537.36"}, "width": 426, "ext": "mp4", "filesize": 29538411, "fps": 25, "acodec": "none"}, {"asr": null, "format_note": "360p", "protocol": "https", "format": "134 - 640x360 (360p)", "tbr": 127.83, "height": 360, "downloader_options": {"http_chunk_size": 10485760}, "format_id": "134", "quality": 2, "container": "mp4_dash", "vbr": 127.83, "url": "https://r2---sn-vgqsknlk.googlevideo.com/videoplayback?expire=1633505259&ei=i_tcYf7RIIiHuQKptJCACw&ip=69.136.135.75&id=o-AJdmr52t8tPQSO674EhiY4P6Z1NXRWqk0fxNUGYJ7Uf3&itag=134&aitags=133%2C134%2C135%2C136%2C137%2C160%2C242%2C243%2C244%2C247%2C248%2C271%2C278%2C394%2C395%2C396%2C397%2C398%2C399%2C400&source=youtube&requiressl=yes&mh=gH&mm=31%2C26&mn=sn-vgqsknlk%2Csn-p5qs7n7z&ms=au%2Conr&mv=m&mvi=2&pl=19&initcwndbps=1862500&vprv=1&mime=video%2Fmp4&ns=hpEngF8VdK4un1lwqFxr5v4G&gir=yes&clen=21385381&dur=1338.360&lmt=1623498577427965&mt=1633483256&fvip=2&keepalive=yes&fexp=24001373%2C24007246&c=WEB&txp=5432434&n=b05Z2SjnPsafJdGn&sparams=expire%2Cei%2Cip%2Cid%2Caitags%2Csource%2Crequiressl%2Cvprv%2Cmime%2Cns%2Cgir%2Cclen%2Cdur%2Clmt&sig=AOq0QJ8wRQIgExOKEOb3keCGTFibdhshdzRxR14wBukLzrQyQacf1agCIQCwlMp4gCzv-NOX-duATbV-CgTup0nBYv_Qd7u7JIDqfQ%3D%3D&lsparams=mh%2Cmm%2Cmn%2Cms%2Cmv%2Cmvi%2Cpl%2Cinitcwndbps&lsig=AG3C_xAwRgIhAIvXvSdhgfnGzXdm5n14CV0O5sPvOlvd3S8O_LYNbllYAiEAkiOwAFx9n9UN7HaBH74Bk59OOUOqK8o1OOOpmw0fkNI%3D", "vcodec": "avc1.4d401e", "http_headers": {"Accept-Charset": "ISO-8859-1,utf-8;q=0.7,*;q=0.7", "Accept-Language": "en-us,en;q=0.5", "Accept-Encoding": "gzip, deflate", "Accept": "text/html,application/xhtml+xml,application/xml;q=0.9,*/*;q=0.8", "User-Agent": "Mozilla/5.0 (Windows NT 10.0; Win64; x64) AppleWebKit/537.36 (KHTML, like Gecko) Chrome/71.0.3578.126 Safari/537.36"}, "width": 640, "ext": "mp4", "filesize": 21385381, "fps": 25, "acodec": "none"}, {"asr": null, "format_note": "360p", "protocol": "https", "format": "243 - 640x360 (360p)", "tbr": 197.071, "height": 360, "downloader_options": {"http_chunk_size": 10485760}, "format_id": "243", "quality": 2, "container": "webm_dash", "vbr": 197.071, "url": "https://r2---sn-vgqsknlk.googlevideo.com/videoplayback?expire=1633505259&ei=i_tcYf7RIIiHuQKptJCACw&ip=69.136.135.75&id=o-AJdmr52t8tPQSO674EhiY4P6Z1NXRWqk0fxNUGYJ7Uf3&itag=243&aitags=133%2C134%2C135%2C136%2C137%2C160%2C242%2C243%2C244%2C247%2C248%2C271%2C278%2C394%2C395%2C396%2C397%2C398%2C399%2C400&source=youtube&requiressl=yes&mh=gH&mm=31%2C26&mn=sn-vgqsknlk%2Csn-p5qs7n7z&ms=au%2Conr&mv=m&mvi=2&pl=19&initcwndbps=1862500&vprv=1&mime=video%2Fwebm&ns=hpEngF8VdK4un1lwqFxr5v4G&gir=yes&clen=32969043&dur=1338.360&lmt=1623500630447766&mt=1633483256&fvip=2&keepalive=yes&fexp=24001373%2C24007246&c=WEB&txp=5432434&n=b05Z2SjnPsafJdGn&sparams=expire%2Cei%2Cip%2Cid%2Caitags%2Csource%2Crequiressl%2Cvprv%2Cmime%2Cns%2Cgir%2Cclen%2Cdur%2Clmt&sig=AOq0QJ8wRQIhAKLpATOW4aWfXi5c3kVYCpG6Im8SOD1G8Y9txbZdVkX4AiAhifvAF-B_MFd5Q6DBCAGmrSfBBPOevnagFIFLqlQL4A%3D%3D&lsparams=mh%2Cmm%2Cmn%2Cms%2Cmv%2Cmvi%2Cpl%2Cinitcwndbps&lsig=AG3C_xAwRgIhAIvXvSdhgfnGzXdm5n14CV0O5sPvOlvd3S8O_LYNbllYAiEAkiOwAFx9n9UN7HaBH74Bk59OOUOqK8o1OOOpmw0fkNI%3D", "vcodec": "vp9", "http_headers": {"Accept-Charset": "ISO-8859-1,utf-8;q=0.7,*;q=0.7", "Accept-Language": "en-us,en;q=0.5", "Accept-Encoding": "gzip, deflate", "Accept": "text/html,application/xhtml+xml,application/xml;q=0.9,*/*;q=0.8", "User-Agent": "Mozilla/5.0 (Windows NT 10.0; Win64; x64) AppleWebKit/537.36 (KHTML, like Gecko) Chrome/71.0.3578.126 Safari/537.36"}, "width": 640, "ext": "webm", "filesize": 32969043, "fps": 25, "acodec": "none"}, {"asr": null, "format_note": "360p", "protocol": "https", "format": "396 - 640x360 (360p)", "tbr": 281.202, "height": 360, "downloader_options": {"http_chunk_size": 10485760}, "format_id": "396", "quality": 2, "container": "mp4_dash", "vbr": 281.202, "url": "https://r2---sn-vgqsknlk.googlevideo.com/videoplayback?expire=1633505259&ei=i_tcYf7RIIiHuQKptJCACw&ip=69.136.135.75&id=o-AJdmr52t8tPQSO674EhiY4P6Z1NXRWqk0fxNUGYJ7Uf3&itag=396&aitags=133%2C134%2C135%2C136%2C137%2C160%2C242%2C243%2C244%2C247%2C248%2C271%2C278%2C394%2C395%2C396%2C397%2C398%2C399%2C400&source=youtube&requiressl=yes&mh=gH&mm=31%2C26&mn=sn-vgqsknlk%2Csn-p5qs7n7z&ms=au%2Conr&mv=m&mvi=2&pl=19&initcwndbps=1862500&vprv=1&mime=video%2Fmp4&ns=hpEngF8VdK4un1lwqFxr5v4G&gir=yes&clen=47043745&dur=1338.360&lmt=1623581104860088&mt=1633483256&fvip=2&keepalive=yes&fexp=24001373%2C24007246&c=WEB&txp=5436432&n=b05Z2SjnPsafJdGn&sparams=expire%2Cei%2Cip%2Cid%2Caitags%2Csource%2Crequiressl%2Cvprv%2Cmime%2Cns%2Cgir%2Cclen%2Cdur%2Clmt&sig=AOq0QJ8wRgIhAJhn1Z-XfAktUALE3M5U05wO43W6V5hTUa8AYm068PrFAiEAoj5KBwtkjGKW_K03ok1uTPR411zpItAkCBURNkAaRs8%3D&lsparams=mh%2Cmm%2Cmn%2Cms%2Cmv%2Cmvi%2Cpl%2Cinitcwndbps&lsig=AG3C_xAwRgIhAIvXvSdhgfnGzXdm5n14CV0O5sPvOlvd3S8O_LYNbllYAiEAkiOwAFx9n9UN7HaBH74Bk59OOUOqK8o1OOOpmw0fkNI%3D", "vcodec": "av01.0.01M.08", "http_headers": {"Accept-Charset": "ISO-8859-1,utf-8;q=0.7,*;q=0.7", "Accept-Language": "en-us,en;q=0.5", "Accept-Encoding": "gzip, deflate", "Accept": "text/html,application/xhtml+xml,application/xml;q=0.9,*/*;q=0.8", "User-Agent": "Mozilla/5.0 (Windows NT 10.0; Win64; x64) AppleWebKit/537.36 (KHTML, like Gecko) Chrome/71.0.3578.126 Safari/537.36"}, "width": 640, "ext": "mp4", "filesize": 47043745, "fps": 25, "acodec": "none"}, {"asr": null, "format_note": "480p", "protocol": "https", "format": "135 - 854x480 (480p)", "tbr": 191.752, "height": 480, "downloader_options": {"http_chunk_size": 10485760}, "format_id": "135", "quality": 3, "container": "mp4_dash", "vbr": 191.752, "url": "https://r2---sn-vgqsknlk.googlevideo.com/videoplayback?expire=1633505259&ei=i_tcYf7RIIiHuQKptJCACw&ip=69.136.135.75&id=o-AJdmr52t8tPQSO674EhiY4P6Z1NXRWqk0fxNUGYJ7Uf3&itag=135&aitags=133%2C134%2C135%2C136%2C137%2C160%2C242%2C243%2C244%2C247%2C248%2C271%2C278%2C394%2C395%2C396%2C397%2C398%2C399%2C400&source=youtube&requiressl=yes&mh=gH&mm=31%2C26&mn=sn-vgqsknlk%2Csn-p5qs7n7z&ms=au%2Conr&mv=m&mvi=2&pl=19&initcwndbps=1862500&vprv=1&mime=video%2Fmp4&ns=hpEngF8VdK4un1lwqFxr5v4G&gir=yes&clen=32079250&dur=1338.360&lmt=1623498543434952&mt=1633483256&fvip=2&keepalive=yes&fexp=24001373%2C24007246&c=WEB&txp=5432434&n=b05Z2SjnPsafJdGn&sparams=expire%2Cei%2Cip%2Cid%2Caitags%2Csource%2Crequiressl%2Cvprv%2Cmime%2Cns%2Cgir%2Cclen%2Cdur%2Clmt&sig=AOq0QJ8wRAIgWBG8KEUtFreVoa8eyqrZOzfscMeDkQ0rWlKYbGTW5zICICVkr9K1kRom9qUB3-5LSAz2fv5kQC7xlBLfL3VkE244&lsparams=mh%2Cmm%2Cmn%2Cms%2Cmv%2Cmvi%2Cpl%2Cinitcwndbps&lsig=AG3C_xAwRgIhAIvXvSdhgfnGzXdm5n14CV0O5sPvOlvd3S8O_LYNbllYAiEAkiOwAFx9n9UN7HaBH74Bk59OOUOqK8o1OOOpmw0fkNI%3D", "vcodec": "avc1.4d401e", "http_headers": {"Accept-Charset": "ISO-8859-1,utf-8;q=0.7,*;q=0.7", "Accept-Language": "en-us,en;q=0.5", "Accept-Encoding": "gzip, deflate", "Accept": "text/html,application/xhtml+xml,application/xml;q=0.9,*/*;q=0.8", "User-Agent": "Mozilla/5.0 (Windows NT 10.0; Win64; x64) AppleWebKit/537.36 (KHTML, like Gecko) Chrome/71.0.3578.126 Safari/537.36"}, "width": 854, "ext": "mp4", "filesize": 32079250, "fps": 25, "acodec": "none"}, {"asr": null, "format_note": "480p", "protocol": "https", "format": "244 - 854x480 (480p)", "tbr": 312.98, "height": 480, "downloader_options": {"http_chunk_size": 10485760}, "format_id": "244", "quality": 3, "container": "webm_dash", "vbr": 312.98, "url": "https://r2---sn-vgqsknlk.googlevideo.com/videoplayback?expire=1633505259&ei=i_tcYf7RIIiHuQKptJCACw&ip=69.136.135.75&id=o-AJdmr52t8tPQSO674EhiY4P6Z1NXRWqk0fxNUGYJ7Uf3&itag=244&aitags=133%2C134%2C135%2C136%2C137%2C160%2C242%2C243%2C244%2C247%2C248%2C271%2C278%2C394%2C395%2C396%2C397%2C398%2C399%2C400&source=youtube&requiressl=yes&mh=gH&mm=31%2C26&mn=sn-vgqsknlk%2Csn-p5qs7n7z&ms=au%2Conr&mv=m&mvi=2&pl=19&initcwndbps=1862500&vprv=1&mime=video%2Fwebm&ns=hpEngF8VdK4un1lwqFxr5v4G&gir=yes&clen=52360050&dur=1338.360&lmt=1623500670418410&mt=1633483256&fvip=2&keepalive=yes&fexp=24001373%2C24007246&c=WEB&txp=5432434&n=b05Z2SjnPsafJdGn&sparams=expire%2Cei%2Cip%2Cid%2Caitags%2Csource%2Crequiressl%2Cvprv%2Cmime%2Cns%2Cgir%2Cclen%2Cdur%2Clmt&sig=AOq0QJ8wRQIhAIkSXC_Om3q1lviK1dG9YdjTowcKi3lf6wR57D-rrgvBAiBDYYKPFqiJQv0NHNo3MZJNanzbJAxKnDZRWp-yfH2uBA%3D%3D&lsparams=mh%2Cmm%2Cmn%2Cms%2Cmv%2Cmvi%2Cpl%2Cinitcwndbps&lsig=AG3C_xAwRgIhAIvXvSdhgfnGzXdm5n14CV0O5sPvOlvd3S8O_LYNbllYAiEAkiOwAFx9n9UN7HaBH74Bk59OOUOqK8o1OOOpmw0fkNI%3D", "vcodec": "vp9", "http_headers": {"Accept-Charset": "ISO-8859-1,utf-8;q=0.7,*;q=0.7", "Accept-Language": "en-us,en;q=0.5", "Accept-Encoding": "gzip, deflate", "Accept": "text/html,application/xhtml+xml,application/xml;q=0.9,*/*;q=0.8", "User-Agent": "Mozilla/5.0 (Windows NT 10.0; Win64; x64) AppleWebKit/537.36 (KHTML, like Gecko) Chrome/71.0.3578.126 Safari/537.36"}, "width": 854, "ext": "webm", "filesize": 52360050, "fps": 25, "acodec": "none"}, {"asr": null, "format_note": "480p", "protocol": "https", "format": "397 - 854x480 (480p)", "tbr": 469.338, "height": 480, "downloader_options": {"http_chunk_size": 10485760}, "format_id": "397", "quality": 3, "container": "mp4_dash", "vbr": 469.338, "url": "https://r2---sn-vgqsknlk.googlevideo.com/videoplayback?expire=1633505259&ei=i_tcYf7RIIiHuQKptJCACw&ip=69.136.135.75&id=o-AJdmr52t8tPQSO674EhiY4P6Z1NXRWqk0fxNUGYJ7Uf3&itag=397&aitags=133%2C134%2C135%2C136%2C137%2C160%2C242%2C243%2C244%2C247%2C248%2C271%2C278%2C394%2C395%2C396%2C397%2C398%2C399%2C400&source=youtube&requiressl=yes&mh=gH&mm=31%2C26&mn=sn-vgqsknlk%2Csn-p5qs7n7z&ms=au%2Conr&mv=m&mvi=2&pl=19&initcwndbps=1862500&vprv=1&mime=video%2Fmp4&ns=hpEngF8VdK4un1lwqFxr5v4G&gir=yes&clen=78517916&dur=1338.360&lmt=1623581104056597&mt=1633483256&fvip=2&keepalive=yes&fexp=24001373%2C24007246&c=WEB&txp=5436432&n=b05Z2SjnPsafJdGn&sparams=expire%2Cei%2Cip%2Cid%2Caitags%2Csource%2Crequiressl%2Cvprv%2Cmime%2Cns%2Cgir%2Cclen%2Cdur%2Clmt&sig=AOq0QJ8wRQIhAKCjSNeWx--aSJLFd1q_fSQ1mR0X3cidSGSYMUlqJ9mJAiAcf8oZSlglt0SbYH_y8ISTt0-AarOdpNJusHHYftEpnw%3D%3D&lsparams=mh%2Cmm%2Cmn%2Cms%2Cmv%2Cmvi%2Cpl%2Cinitcwndbps&lsig=AG3C_xAwRgIhAIvXvSdhgfnGzXdm5n14CV0O5sPvOlvd3S8O_LYNbllYAiEAkiOwAFx9n9UN7HaBH74Bk59OOUOqK8o1OOOpmw0fkNI%3D", "vcodec": "av01.0.04M.08", "http_headers": {"Accept-Charset": "ISO-8859-1,utf-8;q=0.7,*;q=0.7", "Accept-Language": "en-us,en;q=0.5", "Accept-Encoding": "gzip, deflate", "Accept": "text/html,application/xhtml+xml,application/xml;q=0.9,*/*;q=0.8", "User-Agent": "Mozilla/5.0 (Windows NT 10.0; Win64; x64) AppleWebKit/537.36 (KHTML, like Gecko) Chrome/71.0.3578.126 Safari/537.36"}, "width": 854, "ext": "mp4", "filesize": 78517916, "fps": 25, "acodec": "none"}, {"asr": null, "format_note": "720p", "protocol": "https", "format": "136 - 1280x720 (720p)", "tbr": 287.514, "height": 720, "downloader_options": {"http_chunk_size": 10485760}, "format_id": "136", "quality": 4, "container": "mp4_dash", "vbr": 287.514, "url": "https://r2---sn-vgqsknlk.googlevideo.com/videoplayback?expire=1633505259&ei=i_tcYf7RIIiHuQKptJCACw&ip=69.136.135.75&id=o-AJdmr52t8tPQSO674EhiY4P6Z1NXRWqk0fxNUGYJ7Uf3&itag=136&aitags=133%2C134%2C135%2C136%2C137%2C160%2C242%2C243%2C244%2C247%2C248%2C271%2C278%2C394%2C395%2C396%2C397%2C398%2C399%2C400&source=youtube&requiressl=yes&mh=gH&mm=31%2C26&mn=sn-vgqsknlk%2Csn-p5qs7n7z&ms=au%2Conr&mv=m&mvi=2&pl=19&initcwndbps=1862500&vprv=1&mime=video%2Fmp4&ns=hpEngF8VdK4un1lwqFxr5v4G&gir=yes&clen=48099812&dur=1338.360&lmt=1623498554250063&mt=1633483256&fvip=2&keepalive=yes&fexp=24001373%2C24007246&c=WEB&txp=5432434&n=b05Z2SjnPsafJdGn&sparams=expire%2Cei%2Cip%2Cid%2Caitags%2Csource%2Crequiressl%2Cvprv%2Cmime%2Cns%2Cgir%2Cclen%2Cdur%2Clmt&sig=AOq0QJ8wRgIhAKLVpzXXv7Pej74dAS7A33bHZ3g1yP39gk5TL6socuyeAiEAjD0N5SmPWEE502rHXNV0g60cAHfnzeH83LVU0yGpuJk%3D&lsparams=mh%2Cmm%2Cmn%2Cms%2Cmv%2Cmvi%2Cpl%2Cinitcwndbps&lsig=AG3C_xAwRgIhAIvXvSdhgfnGzXdm5n14CV0O5sPvOlvd3S8O_LYNbllYAiEAkiOwAFx9n9UN7HaBH74Bk59OOUOqK8o1OOOpmw0fkNI%3D", "vcodec": "avc1.4d401f", "http_headers": {"Accept-Charset": "ISO-8859-1,utf-8;q=0.7,*;q=0.7", "Accept-Language": "en-us,en;q=0.5", "Accept-Encoding": "gzip, deflate", "Accept": "text/html,application/xhtml+xml,application/xml;q=0.9,*/*;q=0.8", "User-Agent": "Mozilla/5.0 (Windows NT 10.0; Win64; x64) AppleWebKit/537.36 (KHTML, like Gecko) Chrome/71.0.3578.126 Safari/537.36"}, "width": 1280, "ext": "mp4", "filesize": 48099812, "fps": 25, "acodec": "none"}, {"asr": null, "format_note": "720p", "protocol": "https", "format": "247 - 1280x720 (720p)", "tbr": 591.583, "height": 720, "downloader_options": {"http_chunk_size": 10485760}, "format_id": "247", "quality": 4, "container": "webm_dash", "vbr": 591.583, "url": "https://r2---sn-vgqsknlk.googlevideo.com/videoplayback?expire=1633505259&ei=i_tcYf7RIIiHuQKptJCACw&ip=69.136.135.75&id=o-AJdmr52t8tPQSO674EhiY4P6Z1NXRWqk0fxNUGYJ7Uf3&itag=247&aitags=133%2C134%2C135%2C136%2C137%2C160%2C242%2C243%2C244%2C247%2C248%2C271%2C278%2C394%2C395%2C396%2C397%2C398%2C399%2C400&source=youtube&requiressl=yes&mh=gH&mm=31%2C26&mn=sn-vgqsknlk%2Csn-p5qs7n7z&ms=au%2Conr&mv=m&mvi=2&pl=19&initcwndbps=1862500&vprv=1&mime=video%2Fwebm&ns=hpEngF8VdK4un1lwqFxr5v4G&gir=yes&clen=98969035&dur=1338.360&lmt=1623500647557020&mt=1633483256&fvip=2&keepalive=yes&fexp=24001373%2C24007246&c=WEB&txp=5432434&n=b05Z2SjnPsafJdGn&sparams=expire%2Cei%2Cip%2Cid%2Caitags%2Csource%2Crequiressl%2Cvprv%2Cmime%2Cns%2Cgir%2Cclen%2Cdur%2Clmt&sig=AOq0QJ8wRQIgFK-3yGzvjsdF_XUNZFWLlkXyAGPgjeIFyGOcvvA2FSMCIQDSyh_XTrzeWnBMYJsvt08_ty-0z7oTux_NFhQ4cnEQPg%3D%3D&lsparams=mh%2Cmm%2Cmn%2Cms%2Cmv%2Cmvi%2Cpl%2Cinitcwndbps&lsig=AG3C_xAwRgIhAIvXvSdhgfnGzXdm5n14CV0O5sPvOlvd3S8O_LYNbllYAiEAkiOwAFx9n9UN7HaBH74Bk59OOUOqK8o1OOOpmw0fkNI%3D", "vcodec": "vp9", "http_headers": {"Accept-Charset": "ISO-8859-1,utf-8;q=0.7,*;q=0.7", "Accept-Language": "en-us,en;q=0.5", "Accept-Encoding": "gzip, deflate", "Accept": "text/html,application/xhtml+xml,application/xml;q=0.9,*/*;q=0.8", "User-Agent": "Mozilla/5.0 (Windows NT 10.0; Win64; x64) AppleWebKit/537.36 (KHTML, like Gecko) Chrome/71.0.3578.126 Safari/537.36"}, "width": 1280, "ext": "webm", "filesize": 98969035, "fps": 25, "acodec": "none"}, {"asr": null, "format_note": "720p", "protocol": "https", "format": "398 - 1280x720 (720p)", "tbr": 818.184, "height": 720, "downloader_options": {"http_chunk_size": 10485760}, "format_id": "398", "quality": 4, "container": "mp4_dash", "vbr": 818.184, "url": "https://r2---sn-vgqsknlk.googlevideo.com/videoplayback?expire=1633505259&ei=i_tcYf7RIIiHuQKptJCACw&ip=69.136.135.75&id=o-AJdmr52t8tPQSO674EhiY4P6Z1NXRWqk0fxNUGYJ7Uf3&itag=398&aitags=133%2C134%2C135%2C136%2C137%2C160%2C242%2C243%2C244%2C247%2C248%2C271%2C278%2C394%2C395%2C396%2C397%2C398%2C399%2C400&source=youtube&requiressl=yes&mh=gH&mm=31%2C26&mn=sn-vgqsknlk%2Csn-p5qs7n7z&ms=au%2Conr&mv=m&mvi=2&pl=19&initcwndbps=1862500&vprv=1&mime=video%2Fmp4&ns=hpEngF8VdK4un1lwqFxr5v4G&gir=yes&clen=136878184&dur=1338.360&lmt=1623581113375173&mt=1633483256&fvip=2&keepalive=yes&fexp=24001373%2C24007246&c=WEB&txp=5436432&n=b05Z2SjnPsafJdGn&sparams=expire%2Cei%2Cip%2Cid%2Caitags%2Csource%2Crequiressl%2Cvprv%2Cmime%2Cns%2Cgir%2Cclen%2Cdur%2Clmt&sig=AOq0QJ8wRgIhAMW7fcHcSpk3SmcSvPQKV2TDzbPp5p42V3vzJQdGwtT1AiEAjgfFrSxnRGy2WYmJkprR3E3fIqS-tlfS1ErCU_sMrmA%3D&lsparams=mh%2Cmm%2Cmn%2Cms%2Cmv%2Cmvi%2Cpl%2Cinitcwndbps&lsig=AG3C_xAwRgIhAIvXvSdhgfnGzXdm5n14CV0O5sPvOlvd3S8O_LYNbllYAiEAkiOwAFx9n9UN7HaBH74Bk59OOUOqK8o1OOOpmw0fkNI%3D", "vcodec": "av01.0.05M.08", "http_headers": {"Accept-Charset": "ISO-8859-1,utf-8;q=0.7,*;q=0.7", "Accept-Language": "en-us,en;q=0.5", "Accept-Encoding": "gzip, deflate", "Accept": "text/html,application/xhtml+xml,application/xml;q=0.9,*/*;q=0.8", "User-Agent": "Mozilla/5.0 (Windows NT 10.0; Win64; x64) AppleWebKit/537.36 (KHTML, like Gecko) Chrome/71.0.3578.126 Safari/537.36"}, "width": 1280, "ext": "mp4", "filesize": 136878184, "fps": 25, "acodec": "none"}, {"asr": null, "format_note": "1080p", "protocol": "https", "format": "248 - 1920x1080 (1080p)", "tbr": 1069.879, "height": 1080, "downloader_options": {"http_chunk_size": 10485760}, "format_id": "248", "quality": 5, "container": "webm_dash", "vbr": 1069.879, "url": "https://r2---sn-vgqsknlk.googlevideo.com/videoplayback?expire=1633505259&ei=i_tcYf7RIIiHuQKptJCACw&ip=69.136.135.75&id=o-AJdmr52t8tPQSO674EhiY4P6Z1NXRWqk0fxNUGYJ7Uf3&itag=248&aitags=133%2C134%2C135%2C136%2C137%2C160%2C242%2C243%2C244%2C247%2C248%2C271%2C278%2C394%2C395%2C396%2C397%2C398%2C399%2C400&source=youtube&requiressl=yes&mh=gH&mm=31%2C26&mn=sn-vgqsknlk%2Csn-p5qs7n7z&ms=au%2Conr&mv=m&mvi=2&pl=19&initcwndbps=1862500&vprv=1&mime=video%2Fwebm&ns=hpEngF8VdK4un1lwqFxr5v4G&gir=yes&clen=178985439&dur=1338.360&lmt=1623500545038583&mt=1633483256&fvip=2&keepalive=yes&fexp=24001373%2C24007246&c=WEB&txp=5432434&n=b05Z2SjnPsafJdGn&sparams=expire%2Cei%2Cip%2Cid%2Caitags%2Csource%2Crequiressl%2Cvprv%2Cmime%2Cns%2Cgir%2Cclen%2Cdur%2Clmt&sig=AOq0QJ8wRgIhAPaw1MIjDj1YDws51D9qONmEGWODLIRPrXRo7faYvBLGAiEAiCVb_m2ttc1p_j-GWupTYmBsZXoyx4erHA_bnk3Psys%3D&lsparams=mh%2Cmm%2Cmn%2Cms%2Cmv%2Cmvi%2Cpl%2Cinitcwndbps&lsig=AG3C_xAwRgIhAIvXvSdhgfnGzXdm5n14CV0O5sPvOlvd3S8O_LYNbllYAiEAkiOwAFx9n9UN7HaBH74Bk59OOUOqK8o1OOOpmw0fkNI%3D", "vcodec": "vp9", "http_headers": {"Accept-Charset": "ISO-8859-1,utf-8;q=0.7,*;q=0.7", "Accept-Language": "en-us,en;q=0.5", "Accept-Encoding": "gzip, deflate", "Accept": "text/html,application/xhtml+xml,application/xml;q=0.9,*/*;q=0.8", "User-Agent": "Mozilla/5.0 (Windows NT 10.0; Win64; x64) AppleWebKit/537.36 (KHTML, like Gecko) Chrome/71.0.3578.126 Safari/537.36"}, "width": 1920, "ext": "webm", "filesize": 178985439, "fps": 25, "acodec": "none"}, {"asr": null, "format_note": "1080p", "protocol": "https", "format": "137 - 1920x1080 (1080p)", "tbr": 1134.371, "height": 1080, "downloader_options": {"http_chunk_size": 10485760}, "format_id": "137", "quality": 5, "container": "mp4_dash", "vbr": 1134.371, "url": "https://r2---sn-vgqsknlk.googlevideo.com/videoplayback?expire=1633505259&ei=i_tcYf7RIIiHuQKptJCACw&ip=69.136.135.75&id=o-AJdmr52t8tPQSO674EhiY4P6Z1NXRWqk0fxNUGYJ7Uf3&itag=137&aitags=133%2C134%2C135%2C136%2C137%2C160%2C242%2C243%2C244%2C247%2C248%2C271%2C278%2C394%2C395%2C396%2C397%2C398%2C399%2C400&source=youtube&requiressl=yes&mh=gH&mm=31%2C26&mn=sn-vgqsknlk%2Csn-p5qs7n7z&ms=au%2Conr&mv=m&mvi=2&pl=19&initcwndbps=1862500&vprv=1&mime=video%2Fmp4&ns=hpEngF8VdK4un1lwqFxr5v4G&gir=yes&clen=189774692&dur=1338.360&lmt=1623499452829587&mt=1633483256&fvip=2&keepalive=yes&fexp=24001373%2C24007246&c=WEB&txp=5432434&n=b05Z2SjnPsafJdGn&sparams=expire%2Cei%2Cip%2Cid%2Caitags%2Csource%2Crequiressl%2Cvprv%2Cmime%2Cns%2Cgir%2Cclen%2Cdur%2Clmt&sig=AOq0QJ8wRAIgctg4AMdxX0l9ZlUXKiwWLm-dZu-mqH_Qlf4CS3guM3ICIBclbCDycggtBgL_q2rt8TsaPEockwS0VcGtYm8Z3ATD&lsparams=mh%2Cmm%2Cmn%2Cms%2Cmv%2Cmvi%2Cpl%2Cinitcwndbps&lsig=AG3C_xAwRgIhAIvXvSdhgfnGzXdm5n14CV0O5sPvOlvd3S8O_LYNbllYAiEAkiOwAFx9n9UN7HaBH74Bk59OOUOqK8o1OOOpmw0fkNI%3D", "vcodec": "avc1.640028", "http_headers": {"Accept-Charset": "ISO-8859-1,utf-8;q=0.7,*;q=0.7", "Accept-Language": "en-us,en;q=0.5", "Accept-Encoding": "gzip, deflate", "Accept": "text/html,application/xhtml+xml,application/xml;q=0.9,*/*;q=0.8", "User-Agent": "Mozilla/5.0 (Windows NT 10.0; Win64; x64) AppleWebKit/537.36 (KHTML, like Gecko) Chrome/71.0.3578.126 Safari/537.36"}, "width": 1920, "ext": "mp4", "filesize": 189774692, "fps": 25, "acodec": "none"}, {"asr": null, "format_note": "1080p", "protocol": "https", "format": "399 - 1920x1080 (1080p)", "tbr": 1318.543, "height": 1080, "downloader_options": {"http_chunk_size": 10485760}, "format_id": "399", "quality": 5, "container": "mp4_dash", "vbr": 1318.543, "url": "https://r2---sn-vgqsknlk.googlevideo.com/videoplayback?expire=1633505259&ei=i_tcYf7RIIiHuQKptJCACw&ip=69.136.135.75&id=o-AJdmr52t8tPQSO674EhiY4P6Z1NXRWqk0fxNUGYJ7Uf3&itag=399&aitags=133%2C134%2C135%2C136%2C137%2C160%2C242%2C243%2C244%2C247%2C248%2C271%2C278%2C394%2C395%2C396%2C397%2C398%2C399%2C400&source=youtube&requiressl=yes&mh=gH&mm=31%2C26&mn=sn-vgqsknlk%2Csn-p5qs7n7z&ms=au%2Conr&mv=m&mvi=2&pl=19&initcwndbps=1862500&vprv=1&mime=video%2Fmp4&ns=hpEngF8VdK4un1lwqFxr5v4G&gir=yes&clen=220585780&dur=1338.360&lmt=1623581115996960&mt=1633483256&fvip=2&keepalive=yes&fexp=24001373%2C24007246&c=WEB&txp=5436432&n=b05Z2SjnPsafJdGn&sparams=expire%2Cei%2Cip%2Cid%2Caitags%2Csource%2Crequiressl%2Cvprv%2Cmime%2Cns%2Cgir%2Cclen%2Cdur%2Clmt&sig=AOq0QJ8wRQIgPc_i-_PQKap2ACOIJQYL-NPXnjIScjwvwsd1weT3m8MCIQCb6ysWXt0iTfrYGIjug-ZYfD4V_QCMOClB0K3NBICMPw%3D%3D&lsparams=mh%2Cmm%2Cmn%2Cms%2Cmv%2Cmvi%2Cpl%2Cinitcwndbps&lsig=AG3C_xAwRgIhAIvXvSdhgfnGzXdm5n14CV0O5sPvOlvd3S8O_LYNbllYAiEAkiOwAFx9n9UN7HaBH74Bk59OOUOqK8o1OOOpmw0fkNI%3D", "vcodec": "av01.0.08M.08", "http_headers": {"Accept-Charset": "ISO-8859-1,utf-8;q=0.7,*;q=0.7", "Accept-Language": "en-us,en;q=0.5", "Accept-Encoding": "gzip, deflate", "Accept": "text/html,application/xhtml+xml,application/xml;q=0.9,*/*;q=0.8", "User-Agent": "Mozilla/5.0 (Windows NT 10.0; Win64; x64) AppleWebKit/537.36 (KHTML, like Gecko) Chrome/71.0.3578.126 Safari/537.36"}, "width": 1920, "ext": "mp4", "filesize": 220585780, "fps": 25, "acodec": "none"}, {"asr": null, "format_note": "1440p", "protocol": "https", "format": "271 - 2560x1440 (1440p)", "tbr": 2465.189, "height": 1440, "downloader_options": {"http_chunk_size": 10485760}, "format_id": "271", "quality": 6, "container": "webm_dash", "vbr": 2465.189, "url": "https://r2---sn-vgqsknlk.googlevideo.com/videoplayback?expire=1633505259&ei=i_tcYf7RIIiHuQKptJCACw&ip=69.136.135.75&id=o-AJdmr52t8tPQSO674EhiY4P6Z1NXRWqk0fxNUGYJ7Uf3&itag=271&aitags=133%2C134%2C135%2C136%2C137%2C160%2C242%2C243%2C244%2C247%2C248%2C271%2C278%2C394%2C395%2C396%2C397%2C398%2C399%2C400&source=youtube&requiressl=yes&mh=gH&mm=31%2C26&mn=sn-vgqsknlk%2Csn-p5qs7n7z&ms=au%2Conr&mv=m&mvi=2&pl=19&initcwndbps=1862500&vprv=1&mime=video%2Fwebm&ns=hpEngF8VdK4un1lwqFxr5v4G&gir=yes&clen=412413854&dur=1338.360&lmt=1623499605169501&mt=1633483256&fvip=2&keepalive=yes&fexp=24001373%2C24007246&c=WEB&txp=5432434&n=b05Z2SjnPsafJdGn&sparams=expire%2Cei%2Cip%2Cid%2Caitags%2Csource%2Crequiressl%2Cvprv%2Cmime%2Cns%2Cgir%2Cclen%2Cdur%2Clmt&sig=AOq0QJ8wRQIhAIjOEi-iB1uQlGR-ODKN51EfIzd7RX0O0CMSFR5DBlMQAiAQSorcy5NMSnkSzreIImg3MendXuAo7DYvkofE6rf5sQ%3D%3D&lsparams=mh%2Cmm%2Cmn%2Cms%2Cmv%2Cmvi%2Cpl%2Cinitcwndbps&lsig=AG3C_xAwRgIhAIvXvSdhgfnGzXdm5n14CV0O5sPvOlvd3S8O_LYNbllYAiEAkiOwAFx9n9UN7HaBH74Bk59OOUOqK8o1OOOpmw0fkNI%3D", "vcodec": "vp9", "http_headers": {"Accept-Charset": "ISO-8859-1,utf-8;q=0.7,*;q=0.7", "Accept-Language": "en-us,en;q=0.5", "Accept-Encoding": "gzip, deflate", "Accept": "text/html,application/xhtml+xml,application/xml;q=0.9,*/*;q=0.8", "User-Agent": "Mozilla/5.0 (Windows NT 10.0; Win64; x64) AppleWebKit/537.36 (KHTML, like Gecko) Chrome/71.0.3578.126 Safari/537.36"}, "width": 2560, "ext": "webm", "filesize": 412413854, "fps": 25, "acodec": "none"}, {"asr": null, "format_note": "1440p", "protocol": "https", "format": "400 - 2560x1440 (1440p)", "tbr": 3254.54, "height": 1440, "downloader_options": {"http_chunk_size": 10485760}, "format_id": "400", "quality": 6, "container": "mp4_dash", "vbr": 3254.54, "url": "https://r2---sn-vgqsknlk.googlevideo.com/videoplayback?expire=1633505259&ei=i_tcYf7RIIiHuQKptJCACw&ip=69.136.135.75&id=o-AJdmr52t8tPQSO674EhiY4P6Z1NXRWqk0fxNUGYJ7Uf3&itag=400&aitags=133%2C134%2C135%2C136%2C137%2C160%2C242%2C243%2C244%2C247%2C248%2C271%2C278%2C394%2C395%2C396%2C397%2C398%2C399%2C400&source=youtube&requiressl=yes&mh=gH&mm=31%2C26&mn=sn-vgqsknlk%2Csn-p5qs7n7z&ms=au%2Conr&mv=m&mvi=2&pl=19&initcwndbps=1862500&vprv=1&mime=video%2Fmp4&ns=hpEngF8VdK4un1lwqFxr5v4G&gir=yes&clen=544468359&dur=1338.360&lmt=1623581117296099&mt=1633483256&fvip=2&keepalive=yes&fexp=24001373%2C24007246&c=WEB&txp=5436432&n=b05Z2SjnPsafJdGn&sparams=expire%2Cei%2Cip%2Cid%2Caitags%2Csource%2Crequiressl%2Cvprv%2Cmime%2Cns%2Cgir%2Cclen%2Cdur%2Clmt&sig=AOq0QJ8wRAIgeO2EYJZ_O4NXeA8Q5QuXEQYzD4gWBiDCPH5ZYwQw-1gCIEGzer5I-PYUAfaBenjBi-9qliXceW1yqmBxydk64zbP&lsparams=mh%2Cmm%2Cmn%2Cms%2Cmv%2Cmvi%2Cpl%2Cinitcwndbps&lsig=AG3C_xAwRgIhAIvXvSdhgfnGzXdm5n14CV0O5sPvOlvd3S8O_LYNbllYAiEAkiOwAFx9n9UN7HaBH74Bk59OOUOqK8o1OOOpmw0fkNI%3D", "vcodec": "av01.0.12M.08", "http_headers": {"Accept-Charset": "ISO-8859-1,utf-8;q=0.7,*;q=0.7", "Accept-Language": "en-us,en;q=0.5", "Accept-Encoding": "gzip, deflate", "Accept": "text/html,application/xhtml+xml,application/xml;q=0.9,*/*;q=0.8", "User-Agent": "Mozilla/5.0 (Windows NT 10.0; Win64; x64) AppleWebKit/537.36 (KHTML, like Gecko) Chrome/71.0.3578.126 Safari/537.36"}, "width": 2560, "ext": "mp4", "filesize": 544468359, "fps": 25, "acodec": "none"}, {"asr": 44100, "format_note": "360p", "protocol": "https", "format": "18 - 640x360 (360p)", "tbr": 375.966, "height": 360, "format_id": "18", "quality": 2, "http_headers": {"Accept-Charset": "ISO-8859-1,utf-8;q=0.7,*;q=0.7", "Accept-Language": "en-us,en;q=0.5", "Accept-Encoding": "gzip, deflate", "Accept": "text/html,application/xhtml+xml,application/xml;q=0.9,*/*;q=0.8", "User-Agent": "Mozilla/5.0 (Windows NT 10.0; Win64; x64) AppleWebKit/537.36 (KHTML, like Gecko) Chrome/71.0.3578.126 Safari/537.36"}, "url": "https://r2---sn-vgqsknlk.googlevideo.com/videoplayback?expire=1633505259&ei=i_tcYf7RIIiHuQKptJCACw&ip=69.136.135.75&id=o-AJdmr52t8tPQSO674EhiY4P6Z1NXRWqk0fxNUGYJ7Uf3&itag=18&source=youtube&requiressl=yes&mh=gH&mm=31%2C26&mn=sn-vgqsknlk%2Csn-p5qs7n7z&ms=au%2Conr&mv=m&mvi=2&pl=19&initcwndbps=1862500&vprv=1&mime=video%2Fmp4&ns=FRyH-EFhcdKqWINxd0nkxfAG&gir=yes&clen=62902352&ratebypass=yes&dur=1338.467&lmt=1623488360344383&mt=1633483256&fvip=2&fexp=24001373%2C24007246&c=WEB&txp=5430434&n=7j78oQMgKhI43w-S&sparams=expire%2Cei%2Cip%2Cid%2Citag%2Csource%2Crequiressl%2Cvprv%2Cmime%2Cns%2Cgir%2Cclen%2Cratebypass%2Cdur%2Clmt&sig=AOq0QJ8wQwIgBxbHR9y4Zhs67rlU5kTUfWn2Ty-X1ptpexJpgby5YTECH3n879gW8dfcmJXS3stz0ZRHoZXPPCQBl5wBlu_aw7w%3D&lsparams=mh%2Cmm%2Cmn%2Cms%2Cmv%2Cmvi%2Cpl%2Cinitcwndbps&lsig=AG3C_xAwRgIhAIvXvSdhgfnGzXdm5n14CV0O5sPvOlvd3S8O_LYNbllYAiEAkiOwAFx9n9UN7HaBH74Bk59OOUOqK8o1OOOpmw0fkNI%3D", "vcodec": "avc1.42001E", "width": 640, "ext": "mp4", "filesize": 62902352, "fps": 25, "acodec": "mp4a.40.2"}, {"asr": 44100, "format_note": "720p", "protocol": "https", "format": "22 - 1280x720 (720p)", "tbr": 416.606, "height": 720, "format_id": "22", "quality": 4, "http_headers": {"Accept-Charset": "ISO-8859-1,utf-8;q=0.7,*;q=0.7", "Accept-Language": "en-us,en;q=0.5", "Accept-Encoding": "gzip, deflate", "Accept": "text/html,application/xhtml+xml,application/xml;q=0.9,*/*;q=0.8", "User-Agent": "Mozilla/5.0 (Windows NT 10.0; Win64; x64) AppleWebKit/537.36 (KHTML, like Gecko) Chrome/71.0.3578.126 Safari/537.36"}, "url": "https://r2---sn-vgqsknlk.googlevideo.com/videoplayback?expire=1633505259&ei=i_tcYf7RIIiHuQKptJCACw&ip=69.136.135.75&id=o-AJdmr52t8tPQSO674EhiY4P6Z1NXRWqk0fxNUGYJ7Uf3&itag=22&source=youtube&requiressl=yes&mh=gH&mm=31%2C26&mn=sn-vgqsknlk%2Csn-p5qs7n7z&ms=au%2Conr&mv=m&mvi=2&pl=19&initcwndbps=1862500&vprv=1&mime=video%2Fmp4&ns=FRyH-EFhcdKqWINxd0nkxfAG&cnr=14&ratebypass=yes&dur=1338.467&lmt=1630579470517411&mt=1633483256&fvip=2&fexp=24001373%2C24007246&c=WEB&txp=5432434&n=7j78oQMgKhI43w-S&sparams=expire%2Cei%2Cip%2Cid%2Citag%2Csource%2Crequiressl%2Cvprv%2Cmime%2Cns%2Ccnr%2Cratebypass%2Cdur%2Clmt&sig=AOq0QJ8wRQIhAOAPEkHfwLBCrllEB4kr4GkKcwEcjbImDHtS3s5VEnOVAiBptpbh78rQC6Vf5uIn6hwTMi2osALmhkKhX-csbIQdKA%3D%3D&lsparams=mh%2Cmm%2Cmn%2Cms%2Cmv%2Cmvi%2Cpl%2Cinitcwndbps&lsig=AG3C_xAwRgIhAIvXvSdhgfnGzXdm5n14CV0O5sPvOlvd3S8O_LYNbllYAiEAkiOwAFx9n9UN7HaBH74Bk59OOUOqK8o1OOOpmw0fkNI%3D", "vcodec": "avc1.64001F", "width": 1280, "ext": "mp4", "filesize": null, "fps": 25, "acodec": "mp4a.40.2"}], "playlist_uploader_id": null, "resolution": null, "width": 2560, "n_entries": 835, "age_limit": 0}